krautcat/__init__.py
krautcat/lastfm/__init__.py
krautcat/lastfm/scrobbler.py
krautcat_pyscrobbler-0.0.1.dist-info/METADATA
krautcat_pyscrobbler-0.0.1.dist-info/WHEEL
krautcat_pyscrobbler-0.0.1.dist-info/entry_points.txt
krautcat_pyscrobbler-0.0.1.dist-info/RECORD
